[
  {
    "timestamp": 1732816750001,
    "data": {
      "elements": [
        {
          "type": "text",
          "id": 5212,
          "attributes": {
            "style": {
              "color": "rgb(0, 0, 0)",
              "font-family": "Arial, sans-serif"
            }
          }
        },
        {
          "type": "text",
          "id": 5213,
          "attributes": {
            "style": {
              "color": "rgb(0, 0, 0)",
              "font-family": "Arial, sans-serif"
            }
          }
        },
        {
          "type": "text",
          "id": 5216,
          "attributes": {
            "style": {
              "color": "rgb(0, 0, 0)",
              "font-family": "Arial, sans-serif"
            }
          }
        },
        {
          "type": "text",
          "id": 5217,
          "attributes": {
            "style": {
              "color": "rgb(0, 0, 0)",
              "font-family": "Arial, sans-serif"
            }
          }
        },
        {
          "type": "text",
          "id": 5218,
          "attributes": {
            "style": {
              "color": "rgb(0, 0, 0)",
              "font-family": "Arial, sans-serif"
            }
          }
        },
        {
          "type": "navbar",
          "id": 5219,
          "attributes": {
            "style": {
              "background-color": "rgba(0, 0, 0, 0)",
              "color": "rgb(255, 255, 255)",
              "font-family": "Arial, sans-serif"
            }
          }
        },
        {
          "type": "text",
          "id": 5220,
          "attributes": {
            "style": {
              "color": "rgb(0, 0, 0)",
              "font-family": "Arial, sans-serif"
            }
          }
        },
        {
          "type": "text",
          "id": 5224,
          "attributes": {
            "style": {
              "color": "rgb(0, 0, 0)",
              "font-family": "Arial, sans-serif"
            }
          }
        },
        {
          "type": "text",
          "id": 5225,
          "attributes": {
            "style": {
              "color": "rgb(0, 0, 0)",
              "font-family": "Arial, sans-serif"
            }
          }
        },
        {
          "type": "text",
          "id": 5242,
          "attributes": {
            "style": {
              "color": "rgb(0, 0, 0)",
              "font-family": "Arial, sans-serif"
            }
          }
        },
        {
          "type": "text",
          "id": 5248,
          "attributes": {
            "style": {
              "color": "rgb(0, 0, 0)",
              "font-family": "Arial, sans-serif"
            }
          }
        },
        {
          "type": "text",
          "id": 5251,
          "attributes": {
            "style": {
              "color": "rgb(0, 0, 0)",
              "font-family": "Arial, sans-serif"
            }
          }
        },
        {
          "type": "text",
          "id": 5252,
          "attributes": {
            "style": {
              "color": "rgb(0, 0, 0)",
              "font-family": "Arial, sans-serif"
            }
          }
        },
        {
          "type": "text",
          "id": 5253,
          "attributes": {
            "style": {
              "color": "rgb(0, 0, 0)",
              "font-family": "Arial, sans-serif"
            }
          }
        },
        {
          "type": "text",
          "id": 5254,
          "attributes": {
            "style": {
              "color": "rgb(0, 0, 0)",
              "font-family": "Arial, sans-serif"
            }
          }
        },
        {
          "type": "text",
          "id": 5255,
          "attributes": {
            "style": {
              "color": "rgb(0, 0, 0)",
              "font-family": "Arial, sans-serif"
            }
          }
        },
        {
          "type": "text",
          "id": 5263,
          "attributes": {
            "style": {
              "color": "rgb(0, 0, 0)",
              "font-family": "Arial, sans-serif"
            }
          }
        },
        {
          "type": "text",
          "id": 5266,
          "attributes": {
            "style": {
              "color": "rgb(0, 0, 0)",
              "font-family": "Arial, sans-serif"
            }
          }
        },
        {
          "type": "text",
          "id": 5269,
          "attributes": {
            "style": {
              "color": "rgb(0, 0, 0)",
              "font-family": "Arial, sans-serif"
            }
          }
        },
        {
          "type": "text",
          "id": 5278,
          "attributes": {
            "style": {
              "color": "rgb(0, 0, 0)",
              "font-family": "Arial, sans-serif"
            }
          }
        },
        {
          "type": "shepherdHeader",
          "id": 5279,
          "attributes": {
            "style": {
              "background-color": "rgb(100, 100, 100)"
            }
          }
        },
        {
          "type": "text",
          "id": 5284,
          "attributes": {
            "style": {
              "color": "rgb(0, 0, 0)",
              "font-family": "Arial, sans-serif"
            }
          }
        },
        {
          "type": "text",
          "id": 5287,
          "attributes": {
            "style": {
              "color": "rgb(0, 0, 0)",
              "font-family": "Arial, sans-serif"
            }
          }
        },
        {
          "type": "text",
          "id": 5288,
          "attributes": {
            "style": {
              "color": "rgb(0, 0, 0)",
              "font-family": "Arial, sans-serif"
            }
          }
        },
        {
          "type": "shepherdButtons",
          "id": 5292,
          "attributes": {
            "style": {
              "background-color": "rgb(0, 128, 0)"
            }
          }
        },
        {
          "type": "text",
          "id": 5296,
          "attributes": {
            "style": {
              "color": "rgb(0, 0, 0)",
              "font-family": "Arial, sans-serif"
            }
          }
        },
        {
          "type": "text",
          "id": 5298,
          "attributes": {
            "style": {
              "color": "rgb(0, 0, 0)",
              "font-family": "Arial, sans-serif"
            }
          }
        },
        {
          "type": "shepherdHeader",
          "id": 5299,
          "attributes": {
            "style": {
              "background-color": "rgb(100, 100, 100)"
            }
          }
        },
        {
          "type": "text",
          "id": 5304,
          "attributes": {
            "style": {
              "color": "rgb(0, 0, 0)",
              "font-family": "Arial, sans-serif"
            }
          }
        },
        {
          "type": "text",
          "id": 5307,
          "attributes": {
            "style": {
              "color": "rgb(0, 0, 0)",
              "font-family": "Arial, sans-serif"
            }
          }
        },
        {
          "type": "text",
          "id": 5308,
          "attributes": {
            "style": {
              "color": "rgb(0, 0, 0)",
              "font-family": "Arial, sans-serif"
            }
          }
        },
        {
          "type": "shepherdButtons",
          "id": 5312,
          "attributes": {
            "style": {
              "background-color": "rgb(0, 128, 0)"
            }
          }
        },
        {
          "type": "shepherdButtons",
          "id": 5314,
          "attributes": {
            "style": {
              "background-color": "rgb(0, 128, 0)"
            }
          }
        },
        {
          "type": "text",
          "id": 5318,
          "attributes": {
            "style": {
              "color": "rgb(0, 0, 0)",
              "font-family": "Arial, sans-serif"
            }
          }
        },
        {
          "type": "text",
          "id": 5320,
          "attributes": {
            "style": {
              "color": "rgb(0, 0, 0)",
              "font-family": "Arial, sans-serif"
            }
          }
        },
        {
          "type": "shepherdHeader",
          "id": 5321,
          "attributes": {
            "style": {
              "background-color": "rgb(100, 100, 100)"
            }
          }
        },
        {
          "type": "text",
          "id": 5326,
          "attributes": {
            "style": {
              "color": "rgb(0, 0, 0)",
              "font-family": "Arial, sans-serif"
            }
          }
        },
        {
          "type": "text",
          "id": 5329,
          "attributes": {
            "style": {
              "color": "rgb(0, 0, 0)",
              "font-family": "Arial, sans-serif"
            }
          }
        },
        {
          "type": "text",
          "id": 5330,
          "attributes": {
            "style": {
              "color": "rgb(0, 0, 0)",
              "font-family": "Arial, sans-serif"
            }
          }
        },
        {
          "type": "shepherdButtons",
          "id": 5334,
          "attributes": {
            "style": {
              "background-color": "rgb(0, 128, 0)"
            }
          }
        },
        {
          "type": "shepherdButtons",
          "id": 5336,
          "attributes": {
            "style": {
              "background-color": "rgb(0, 128, 0)"
            }
          }
        },
        {
          "type": "background",
          "id": 301,
          "attributes": {
            "style": {
              "background-color": "rgb(255, 255, 255)"
            }
          }
        }
      ]
    }
  }
]